{"classFile":"ComplexTest","className":"ComplexTest","packages":"org.apache.commons.numbers.complex","methodInfos":[{"md5":"an66Odxo1fqJUgN/ECUjJw==","methodName":"testConstructor","parameters":"[]"},{"md5":"zB4IL1nagrlywKw4ppPfJw==","methodName":"testConstructorNaN","parameters":"[]"},{"md5":"tN3/kX3/1KhGqeKjVfiliA==","methodName":"testAbs","parameters":"[]"},{"md5":"OYZSy2NEntr95FVMlqeHDQ==","methodName":"testAbsNaN","parameters":"[]"},{"md5":"BPD6NzNck/ZAzDe4iG8KdQ==","methodName":"testAdd","parameters":"[]"},{"md5":"/kLnNFDe4uXq0UEPCODk1Q==","methodName":"testAddInf","parameters":"[]"},{"md5":"6K89d9CnQjLk0hRf3u9FGw==","methodName":"testScalarAdd","parameters":"[]"},{"md5":"POT5mj8/bWKWSHI+M1RLZg==","methodName":"testScalarAddNaN","parameters":"[]"},{"md5":"9MCD7OYHFJiaRCtYmvNOHw==","methodName":"testScalarAddInf","parameters":"[]"},{"md5":"t4IOpZ5TQwBpwGaACK8XqQ==","methodName":"testConjugate","parameters":"[]"},{"md5":"uyilX8a3rC1evDTdUFnHqw==","methodName":"testConjugateInfiinite","parameters":"[]"},{"md5":"IuF+TI/6xy8HcEurRjfnUA==","methodName":"testDivide","parameters":"[]"},{"md5":"QRbBR9KBjp+KI6aRqYhzqA==","methodName":"testDivideReal","parameters":"[]"},{"md5":"4guCV6cyA91O4T87mkeAqw==","methodName":"testDivideImaginary","parameters":"[]"},{"md5":"e4lF6HZ7hVTbMaVRgH6iiA==","methodName":"testDivideZero","parameters":"[]"},{"md5":"1wPeOHOGuLWjl+2BJntRog==","methodName":"testDivideZeroZero","parameters":"[]"},{"md5":"bVyJyCQLrWrAuNvgEFpioQ==","methodName":"testDivideNaN","parameters":"[]"},{"md5":"hptThzEYJTqUNlNziYygFw==","methodName":"testScalarDivide","parameters":"[]"},{"md5":"02DnK39/uT63MD8fsZ8AtA==","methodName":"testScalarDivideNaN","parameters":"[]"},{"md5":"jLuVSqjy4XoUzKs9WKEgeg==","methodName":"testScalarDivideZero","parameters":"[]"},{"md5":"dtq0dUKdcnktwR0SmosHiA==","methodName":"testReciprocal","parameters":"[]"},{"md5":"EwoSa9ydL0K03vvSRBLiXg==","methodName":"testReciprocalReciprocal","parameters":"[]"},{"md5":"kqeJ4wAbh/GJQ4En004uxg==","methodName":"testReciprocalReal","parameters":"[]"},{"md5":"eKLD66StUtlXb9EtQr7efw==","methodName":"testReciprocalImaginary","parameters":"[]"},{"md5":"h2rHOh9Wh1vVPKDnFMAuvA==","methodName":"testMultiply","parameters":"[]"},{"md5":"m6ylX71Kid2rVXpzRYEd2A==","methodName":"testScalarMultiply","parameters":"[]"},{"md5":"8O+Sdso9GUzPixjLzSy+6A==","methodName":"testScalarMultiplyNaN","parameters":"[]"},{"md5":"j2dncnvuDynneXVZq4+EpQ==","methodName":"testScalarMultiplyInf","parameters":"[]"},{"md5":"/egufk5vAGiCnr3z71ZKNw==","methodName":"testNegate","parameters":"[]"},{"md5":"naXz68plVTf0sHpLkdyExA==","methodName":"testSubtract","parameters":"[]"},{"md5":"c3tFVHmoIMS5dZI/FBGZeg==","methodName":"testSubtractInf","parameters":"[]"},{"md5":"nI+VvCJAaKg+zHm7uBMM6Q==","methodName":"testScalarSubtract","parameters":"[]"},{"md5":"4duybCepQUpD5cHdjq2LRg==","methodName":"testScalarSubtractNaN","parameters":"[]"},{"md5":"qFudTE4xCNacPUb433i+mw==","methodName":"testScalarSubtractInf","parameters":"[]"},{"md5":"hy1cjro0TUY+JoyDUT2thw==","methodName":"testEqualsNull","parameters":"[]"},{"md5":"S9IbprTdoN1Kq9O72QtkOQ==","methodName":"testFloatingPointEqualsPrecondition1","parameters":"[]"},{"md5":"zYlw73dc7OmXGu+fFbJ1gw==","methodName":"testFloatingPointEqualsPrecondition2","parameters":"[]"},{"md5":"YwM/G6PGZEBKm7Ljnd004w==","methodName":"testEqualsClass","parameters":"[]"},{"md5":"ehh1bkeIcpPSQVveE/2cxQ==","methodName":"testEqualsSame","parameters":"[]"},{"md5":"A7zxHiQcjYz1nMb9xGAPwQ==","methodName":"testFloatingPointEquals","parameters":"[]"},{"md5":"3wui/yms/STzOIsFiLc5rw==","methodName":"testFloatingPointEqualsNaN","parameters":"[]"},{"md5":"FVGCDjxGO5Hjp/T2p1NaUA==","methodName":"testFloatingPointEqualsWithAllowedDelta","parameters":"[]"},{"md5":"/R4kQ5eLeQXIpCyEvj5W3g==","methodName":"testFloatingPointEqualsWithAllowedDeltaNaN","parameters":"[]"},{"md5":"sZijPg7WAeZFh6AjBEIv+w==","methodName":"testFloatingPointEqualsWithRelativeTolerance","parameters":"[]"},{"md5":"pEm9yXFFSGenjRqts86tEQ==","methodName":"testFloatingPointEqualsWithRelativeToleranceNaN","parameters":"[]"},{"md5":"j/zlXaHYiji+pLxEiuusgQ==","methodName":"testEqualsTrue","parameters":"[]"},{"md5":"HkC11Ny4ti8uzLBjuy5FPw==","methodName":"testEqualsRealDifference","parameters":"[]"},{"md5":"4joqmKm5gM1EUgVQiTNF6w==","methodName":"testEqualsImaginaryDifference","parameters":"[]"},{"md5":"le6PuGQ2MxgTuB0yYMqKjA==","methodName":"testHashCode","parameters":"[]"},{"md5":"gNSdzzIDv3gyFYFSy4078g==","methodName":"testScalarPow","parameters":"[]"},{"md5":"aY5fitwqGVVhuaLEq3VRrQ==","methodName":"testScalarPowNaNBase","parameters":"[]"},{"md5":"YTkcuPP9vmZaSEEcWmT+wA==","methodName":"testScalarPowNaNExponent","parameters":"[]"},{"md5":"AOgZGGV7PldbpP0cJ/HreA==","methodName":"testSqrt1z","parameters":"[]"},{"md5":"REmimA9gUjsZVW8iJ2qhOg==","methodName":"testNthRoot_normal_thirdRoot","parameters":"[]"},{"md5":"8Zjo0YtGi2J0VLm8sQmnow==","methodName":"testNthRoot_normal_fourthRoot","parameters":"[]"},{"md5":"r9JyuxbsDG/n9nmYhTuSZA==","methodName":"testNthRoot_cornercase_thirdRoot_imaginaryPartEmpty","parameters":"[]"},{"md5":"C2V7Jw1Fmg1u2DZbvA70DA==","methodName":"testNthRoot_cornercase_thirdRoot_realPartZero","parameters":"[]"},{"md5":"mTJelnVdr+5GRmcVWA8U5Q==","methodName":"testGetArgument","parameters":"[]"}],"addLines":[37,38,39,40,41,42,43,44,45,46,47,48,49,50,51,52,53,54,55,59,66,69,72,78,85,91,92,100,101,106,113,115,121,123,129,132,135,141,155,157,163,164,172,173,174,180,181,182,187,195,202,224,226,232,234,240,246,256,265,266,271,272,282,283,297,299,302,308,310,316,318,322,328,342,343,351,352,357,363,365,371,373,379,381,384,391,397,401,406,412,421,422,432,437,443,446,455,456,465,466,479,480,486,487,495,496,502,503,509,510,516,517,519,521,522,531,532,536,537,573,575,583,589,591,612,613,636,668,702,733,754,757,760,763,766,769,772,775,808],"delLines":[37,38,39,40,41,42,43,44,45,46,47,48,49,50,51,52,53,54,55,59,66,69,72,78,85,91,92,100,101,106,113,115,121,123,129,132,135,141,155,157,163,164,172,173,174,180,181,182,187,195,202,224,226,232,234,240,246,256,265,266,271,272,282,283,297,299,302,308,310,316,318,322,328,342,343,351,352,357,363,365,371,373,379,381,384,391,397,401,406,412,421,422,432,437,443,446,455,456,465,466,479,480,486,487,495,496,502,503,509,510,516,517,519,521,522,531,532,536,537,573,575,583,589,591,612,613,636,668,702,733,754,757,760,763,766,769,772,775,808,843,844,845,846,847],"type":"MODIFY","path":"commons-numbers-complex/src/test/java/org/apache/commons/numbers/complex/ComplexTest.java","pro_Commit":"5166d4beb42c1a71314312197d247ede015c2050","pro_Date":"2018-03-01 21:01:48","sha1":"e147fe0172ecfa2bb39081370cdff50e6e682c58","file_Date":"2018-03-01 21:14:40","projectName":"commons-numbers","commitID":"b867022591eb365476d0df3dce3e1d559369d011"}