{"classFile":"DocumentTest","className":"DocumentTest","packages":"org.jsoup.nodes","methodInfos":[{"md5":"vSWpVdhzOxoNu+KbSzMUCA==","methodName":"testShiftJisRoundtrip","parameters":"[]"}],"addLines":[3,6,387,388,389,390,391,392,393,394,395,396,397,398,399,400,401,402,403,404,405,406,407,408,409],"delLines":[],"type":"MODIFY","path":"src/test/java/org/jsoup/nodes/DocumentTest.java","pro_Commit":"373ea35b2cb227b56694aa50589c853b68caa03a","pro_Date":"2015-04-18 06:06:06","sha1":"4ed2b36247aac779d17dd7130568165c0e5fb643","file_Date":"2015-07-06 14:45:23","projectName":"jsoup","commitID":"3ba88d8c2ab500c07f9e2ddbc07a4bd01fadbd78"}