{"classFile":"StringArrayConverterTestCase","className":"StringArrayConverterTestCase","packages":"org.apache.commons.beanutils2.converters","methodInfos":[{"md5":"FngGaw6Pc7/666VOOKNLNA==","methodName":"StringArrayConverterTestCase","parameters":"[final String name]"},{"md5":"UMrmcc3DLi6yZ1RSHN1RkQ==","methodName":"testIntToString","parameters":"[]"}],"addLines":[],"delLines":[1,2,3,4,5,6,7,8,9,10,11,12,13,14,15,16,17,18,19,20,21,22,23,24,25,26,27,28,29,30,31,32,33,34,35,36,37,38,39,40,41,42,43,44,45,46,47,48,49],"type":"DELETE","path":"src/test/java/org/apache/commons/beanutils2/converters/StringArrayConverterTestCase.java","pro_Commit":"693d479e5476a234828cb6d4194d933acfe6b870","label":null,"predict":null,"commitID":"693d479e5476a234828cb6d4194d933acfe6b870","pro_Date":"2018-10-09 02:20:28","file_Date":"2018-10-09 02:20:28","projectName":"commons-beanutils","sha1":"9fb95d30966db8a750a5b7161e92cf275fd017eb","pro_Path":null}