{"repository":"logging-log4j2","prod_path":"log4j-core/src/main/java/org/apache/logging/log4j/core/util/Throwables.java","test_path":"log4j-core/src/test/java/org/apache/logging/log4j/core/util/ThrowablesTest.java","prod_time":"2015-09-28 01:49:28","test_time":"2016-06-07 08:24:09","add_annotation_line":0,"add_call_line":0,"add_classname_line":0,"add_condition_line":0,"add_field_line":0,"add_import_line":0,"add_packageid_line":0,"add_parameter_line":0,"add_return_line":0,"del_annotation_line":0,"del_call_line":0,"del_classname_line":0,"del_condition_line":0,"del_field_line":0,"del_import_line":0,"del_packageid_line":0,"del_parameter_line":0,"del_return_line":0,"label":"NEGATIVE","pro_Commit":"decf01d0d08756dda5e55feee5749ede0791b030","test_Commit":"9ec2b5bee38c4913b520211c2cb9105b53f65c93","true_label":null}