{"classFile":"InferenceTestUtilsTest","className":"InferenceTestUtilsTest","packages":"org.apache.commons.math4.stat.inference","methodInfos":[{"md5":"yi2fKEinm0n/qU5Ps68mGA==","methodName":"testKSOneSample","parameters":"[]"},{"md5":"UWhkZsFhWIndpeQRFC3S+g==","methodName":"testKSTwoSample","parameters":"[]"}],"addLines":[535,542,549,552],"delLines":[40,536,543,550,551,554,555],"type":"MODIFY","path":"src/test/java/org/apache/commons/math4/stat/inference/InferenceTestUtilsTest.java","pro_Commit":"10e38114032cb4c585b29e946e1d70e05d52a878","pro_Date":"2017-05-10 20:41:17","sha1":"aa6b10f52f1237b39a7962d060d2556adb42417a","file_Date":"2017-05-10 21:31:56","projectName":"commons-math","commitID":"0f3648f749b7b67c2c61282297569657ea6220dd"}