{"classFile":"AdamsMoultonFieldIntegratorTest","className":"AdamsMoultonFieldIntegratorTest","packages":"org.apache.commons.math4.ode.nonstiff","methodInfos":[{"md5":"yOi7b3cMAoGv8iC7FaGEag==","methodName":"createIntegrator","parameters":"[Field<T> field, final int nSteps, final double minStep, final double maxStep, final double scalAbsoluteTolerance, final double scalRelativeTolerance]"},{"md5":"DzRX7mrlf5fJ5o03mu6ndg==","methodName":"createIntegrator","parameters":"[Field<T> field, final int nSteps, final double minStep, final double maxStep, final double[] vecAbsoluteTolerance, final double[] vecRelativeTolerance]"},{"md5":"c51pblQoez6HfCqEVddIjA==","methodName":"testMinStep","parameters":"[]"},{"md5":"sjkgzTbBTEe4oCWCAZO5hg==","methodName":"testIncreasingTolerance","parameters":"[]"},{"md5":"Ww96FiK92/VNXdAzx4JtHg==","methodName":"exceedMaxEvaluations","parameters":"[]"},{"md5":"KTxE8Mw9zDJuH4R9sqggWw==","methodName":"backward","parameters":"[]"},{"md5":"Pm8Teu58kH/IRRqwmR4rug==","methodName":"polynomial","parameters":"[]"},{"md5":"PN/zNgTApipWhmUcVBdJXg==","methodName":"testStartFailure","parameters":"[]"}],"addLines":[1,2,3,4,5,6,7,8,9,10,11,12,13,14,15,16,17,18,19,20,21,22,23,24,25,26,27,28,29,30,31,32,33,34,35,36,37,38,39,40,41,42,43,44,45,46,47,48,49,50,51,52,53,54,55,56,57,58,59,60,61,62,63,64,65,66,67,68,69,70,71,72,73,74,75,76,77,78],"delLines":[],"type":"ADD","path":"src/test/java/org/apache/commons/math4/ode/nonstiff/AdamsMoultonFieldIntegratorTest.java","pro_Commit":"82cf2774a215ae46477e4b35decf77321e20ab34","pro_Date":"2016-01-06 21:19:07","sha1":"c44124a4e74bfabe0b5229fdc9b269a0a4460e61","file_Date":"2016-01-06 21:19:07","projectName":"commons-math","commitID":"82cf2774a215ae46477e4b35decf77321e20ab34"}