{"classFile":"FieldLUDecompositionTest","className":"FieldLUDecompositionTest","packages":"org.apache.commons.math4.linear","methodInfos":[{"md5":"8m2aRDL8wgSnTJ0F0L0qng==","methodName":"testDimensions","parameters":"[]"},{"md5":"u511yWCkDuBr9EXgK9ItuA==","methodName":"testNonSquare","parameters":"[]"},{"md5":"0/oYHN5uyBg8AtWiixgbUg==","methodName":"testPAEqualLU","parameters":"[]"},{"md5":"y6IF9VqEKg2ILzgWvkm3qw==","methodName":"testLLowerTriangular","parameters":"[]"},{"md5":"sAflNobr7xnJbLugnF7GqQ==","methodName":"testUUpperTriangular","parameters":"[]"},{"md5":"vIVloRYiLsQd33tKbLC9GQ==","methodName":"testPPermutation","parameters":"[]"},{"md5":"JvH7FRVg37YDXgius9OE4g==","methodName":"testSingular","parameters":"[]"},{"md5":"Ijx76MR+81RPoOs/i8uM8w==","methodName":"testMatricesValues1","parameters":"[]"},{"md5":"v0mlJnX+lgMlry1Ur3PAZA==","methodName":"testMatricesValues2","parameters":"[]"}],"addLines":[23,24,31,32,33,34,36,37,38,39,41,42,43,44,48,49,50,52,53,54,55,56,62,63,64,78,79,80,81,82,93,94,95,96,97,100,107,109,117,124,136,137,139,141,149,150,153,161,162,164,165,166,169,178,179,181,197,198,200,217,218,220,222,229,230,231,232,233,234,236,237,238,239,241,242,243,244,249,251,253,270,271,272,273,274,275,277,278,279,280,282,283,284,285,290,292,294],"delLines":[23,24,31,32,33,34,36,37,38,39,41,42,43,44,48,49,50,52,53,54,55,56,62,63,64,78,79,80,81,82,93,94,95,96,97,100,107,109,117,124,136,137,139,141,149,150,153,161,162,164,165,166,169,178,179,181,197,198,200,217,218,220,222,229,230,231,232,233,234,236,237,238,239,241,242,243,244,249,251,253,270,271,272,273,274,275,277,278,279,280,282,283,284,285,290,292,294],"type":"MODIFY","path":"src/test/java/org/apache/commons/math4/linear/FieldLUDecompositionTest.java","pro_Commit":"762eb53f5cee901be190cd324dfde01977aeea60","pro_Date":"2016-09-21 01:37:01","sha1":"df74ca65c03152184051aa303cd665591f69e364","file_Date":"2019-12-03 19:53:05","projectName":"commons-math","commitID":"b8d96de5871d938f678b4702c2fcc306bdf1f34d"}