{"classFile":"JmsConnectionIdTest","className":"JmsConnectionIdTest","packages":"org.apache.qpid.jms.meta","methodInfos":[{"md5":"X5xCmVSB94v++dDqibzCAg==","methodName":"setUp","parameters":"[]"},{"md5":"aWptk6wE5gsH20PskfWTYw==","methodName":"testCreateFromStringThrowsWhenNull","parameters":"[]"},{"md5":"Y7hcnF81sCbaB2BXDCMxQA==","methodName":"testCreateFromStringThrowsWhenEmpty","parameters":"[]"},{"md5":"v50vwQIKOvCzCcA6Q7Zpig==","methodName":"testCreateFromConnectionIdThrowsWhenNull","parameters":"[]"},{"md5":"5rFoUqeqpGRDmumx1B9FLg==","methodName":"testCreateFromSessionIdThrowsWhenNull","parameters":"[]"},{"md5":"xEz+jpPmb6AjW2V3d8HA1Q==","methodName":"testCreateFromProducerIdThrowsWhenNull","parameters":"[]"},{"md5":"DryXcZJmy7XosBcHKa7VSQ==","methodName":"testCreateFromConsumerIdThrowsWhenNull","parameters":"[]"},{"md5":"TWrGP1FOKVnAoZx0KbSuHA==","methodName":"testStringConstructor","parameters":"[]"},{"md5":"jTXTKIdFFgMSS0w82h0DyA==","methodName":"testProviderHints","parameters":"[]"},{"md5":"US2JGpX5QkZoheEX80/Ohg==","methodName":"testJmsConnectionIdFromJmsConnectionId","parameters":"[]"},{"md5":"3Bi4bsFJww+wisnRFMLAwg==","methodName":"testJmsConnectionIdFromJmsSessionId","parameters":"[]"},{"md5":"pDWRVLPsOk9Y+xfLeIw8lg==","methodName":"testJmsConnectionIdFromJmsConsumerId","parameters":"[]"},{"md5":"UsBU4XeRaTdTNhh0hhxQog==","methodName":"testJmsConnectionIdFromJmsProducerId","parameters":"[]"},{"md5":"1pIZz0lTgvQLVQJ8Ea9ayA==","methodName":"testCompareTo","parameters":"[]"},{"md5":"d/xfS7Ih4WK/O/gy976n4Q==","methodName":"testEquals","parameters":"[]"},{"md5":"MIc9bFbIBKQm3J91ijj+lw==","methodName":"testHashCode","parameters":"[]"}],"addLines":[1,2,3,4,5,6,7,8,9,10,11,12,13,14,15,16,17,18,19,20,21,22,23,24,25,26,27,28,29,30,31,32,33,34,35,36,37,38,39,40,41,42,43,44,45,46,47,48,49,50,51,52,53,54,55,56,57,58,59,60,61,62,63,64,65,66,67,68,69,70,71,72,73,74,75,76,77,78,79,80,81,82,83,84,85,86,87,88,89,90,91,92,93,94,95,96,97,98,99,100,101,102,103,104,105,106,107,108,109,110,111,112,113,114,115,116,117,118,119,120,121,122,123,124,125,126,127,128,129,130,131,132,133,134,135,136,137,138,139,140,141,142,143,144,145,146,147,148,149,150,151,152,153,154,155,156,157,158,159,160,161,162,163,164,165,166,167],"delLines":[],"type":"ADD","path":"qpid-jms-client/src/test/java/org/apache/qpid/jms/meta/JmsConnectionIdTest.java","pro_Commit":"6973cb51db39ade0e741580dc15bbc11eafa5f98","pro_Date":"2014-10-08 03:50:15","sha1":"6164fb1f09d77727ad6f68db2f89a9e187a453cb","file_Date":"2014-10-08 03:50:15","projectName":"qpid-jms","commitID":"6973cb51db39ade0e741580dc15bbc11eafa5f98"}