{"classFile":"ReservoirLongsSketchTest","className":"ReservoirLongsSketchTest","packages":"com.yahoo.sketches.sampling","methodInfos":[{"md5":"6dnWjdyvzeJytRx+vWvzkQ==","methodName":"checkVersionConversion","parameters":"[]"}],"addLines":[5,6,249,250,251,252,253,254,255,256,257,258,259,260,261,262,263,264,265,266,267,268,269,270,271,272,273,274],"delLines":[],"type":"MODIFY","path":"sketches/src/test/java/com/yahoo/sketches/sampling/ReservoirLongsSketchTest.java","pro_Commit":"fb9a5e5b7b99cac286aa32bbbda858d72114207f","pro_Date":"2016-11-11 17:16:03","sha1":"97a8f90a1b6f30355f0287c9bb2af65af3d7109b","file_Date":"2016-11-11 17:16:03","projectName":"datasketches-java","commitID":"fb9a5e5b7b99cac286aa32bbbda858d72114207f"}