{"classFile":"ByteArrayUtilTest","className":"ByteArrayUtilTest","packages":"org.apache.datasketches","methodInfos":[{"md5":"yBWqHn/b972R2cWjpIXKpA==","methodName":"checkGetPutShortLE","parameters":"[]"},{"md5":"LaDDvmJn3EE3QfOHRvm/Fg==","methodName":"checkGetPutShortBE","parameters":"[]"},{"md5":"uFw1oDXJGzYIUFsWKxknmw==","methodName":"checkGetPutIntLE","parameters":"[]"},{"md5":"QAkef2pJqcsoMGuBrIknLw==","methodName":"checkGetPutIntBE","parameters":"[]"},{"md5":"BQiA9c7I6DEhEG/WfwtcCg==","methodName":"checkGetPutLongLE","parameters":"[]"},{"md5":"W1Ynd4I9NsZue5dz02kNcQ==","methodName":"checkGetPutLongBE","parameters":"[]"},{"md5":"lvXEz+aYwX3zOfiqijmuQw==","methodName":"checkGetPutFloatLE","parameters":"[]"},{"md5":"FJ/tFmwiNjaSaNHJZMChbQ==","methodName":"checkGetPutFloatBE","parameters":"[]"},{"md5":"fpye7GFObe6oBg8xL6q01A==","methodName":"checkGetPutDoubleLE","parameters":"[]"},{"md5":"WUyY+L4XXZ75dbGGjC21iw==","methodName":"checkGetPutDoubleBE","parameters":"[]"}],"addLines":[54,55,56,57,65,66,67,68,76,77,78,79,87,88,89,90,99,100,101,102,110,111,112,113,121,122,123,124,134,135,136,137,145,146,147,148,158,159,160,161],"delLines":[54,55,56,57,65,66,67,68,76,77,78,79,87,88,89,90,99,100,101,102,110,111,112,113,121,122,123,124,134,135,136,137,145,146,147,148,158,159,160,161],"type":"MODIFY","path":"src/test/java/org/apache/datasketches/ByteArrayUtilTest.java","pro_Commit":"No corresponding product modification found","pro_Date":null,"sha1":"a372e67e8aba961bb256fa6d428560b191394e80","file_Date":"2019-11-26 08:57:27","projectName":"datasketches-java","commitID":"71133e1f5828a570783dc1aa7cbca071118cd856"}