{"classFile":"ConcurrentHeapQuickSelectSketchTest","className":"ConcurrentHeapQuickSelectSketchTest","packages":"com.yahoo.sketches.theta","methodInfos":[{"md5":"ibLwBWw1fqz2diG20f/a0g==","methodName":"checkBadSerVer","parameters":"[]"},{"md5":"sQVi70vVjIB2ShzMaBDYsQ==","methodName":"checkPropagationNotOrdered","parameters":"[]"},{"md5":"KrK2Uh9iKBRALm/jA0dtDA==","methodName":"checkIllegalSketchID_UpdateSketch","parameters":"[]"},{"md5":"8kFWYUQeoOv0DEXMFKMrFg==","methodName":"checkHQStoCompactForms","parameters":"[]"},{"md5":"9C36obMJk6u7eRivBi/Afg==","methodName":"checkHQStoCompactEmptyForms","parameters":"[]"},{"md5":"lPwqFhECN06UT7jZCtHf4w==","methodName":"checkExactMode","parameters":"[]"},{"md5":"c8qYPuppKgLc4MHW0aCrCQ==","methodName":"checkEstMode","parameters":"[]"},{"md5":"1Lwzq6/Kn+EXtApLvFPcdw==","methodName":"checkRebuild","parameters":"[]"},{"md5":"ZIL3g8wKMdY5NAdUm7xBeg==","methodName":"checkResetAndStartingSubMultiple","parameters":"[]"},{"md5":"SqQwJdkVLog9ViK5v2K3tQ==","methodName":"checkDQStoCompactEmptyForms","parameters":"[]"},{"md5":"yN0s++x7wuw3cAwJoVzuAA==","methodName":"checkBackgroundPropagation","parameters":"[]"},{"md5":"cRoqawgegRaD68lyXHB6IA==","methodName":"buildConcSketch","parameters":"[]"},{"md5":"T4ujAfbUA5WORh55DW1jlA==","methodName":"waitForPropagationToComplete","parameters":"[]"}],"addLines":[32,42,74,98,242,321,369,391,448,511,539,614,662,710,717],"delLines":[41,73,97,241,320,368,390,447,510,538,613,661],"type":"MODIFY","path":"src/test/java/com/yahoo/sketches/theta/ConcurrentHeapQuickSelectSketchTest.java","pro_Commit":"b7850ff93376a41f28320142de884530124d7da6","pro_Date":"2018-11-19 00:26:48","sha1":"eaba117ca52dbad7210639bf695c4c167312b5b3","file_Date":"2018-11-19 01:11:55","projectName":"datasketches-java","commitID":"2f562d3b1d869a6fe151ec923befbd5a526ae337"}