{"classFile":"CouponListTest","className":"CouponListTest","packages":"com.yahoo.sketches.hll","methodInfos":[{"md5":"fAL7NC3FmU1fWDqEfUQoAw==","methodName":"checkDuplicatesAndMisc","parameters":"[boolean direct]"}],"addLines":[63,73,85],"delLines":[63,73,85],"type":"MODIFY","path":"src/test/java/com/yahoo/sketches/hll/CouponListTest.java","pro_Commit":"d5868038297a4954929b3f7c9c9d184f92d3f132","pro_Date":"2018-10-25 04:18:08","sha1":"1e1bb4d2e764e2fb607f3de070a9e2379c95be9e","file_Date":"2018-10-25 04:18:08","projectName":"datasketches-java","commitID":"d5868038297a4954929b3f7c9c9d184f92d3f132"}