{"classFile":"UnionTest","className":"UnionTest","packages":"com.yahoo.sketches.hll","methodInfos":[{"md5":"nwz8p0MCwkN5ZdICYGVmmQ==","methodName":"checkUnionWithWrap","parameters":"[]"}],"addLines":[348,349,350,351,352,353,354,355,356,357,358,359,360,361,363,364,365],"delLines":[],"type":"MODIFY","path":"src/test/java/com/yahoo/sketches/hll/UnionTest.java","pro_Commit":"212459a88c517d634549745334821e7903219705","pro_Date":"2017-08-25 02:14:45","sha1":"4d6d1ed713bed8fcb65979c790cb69aeeee7c90e","file_Date":"2017-08-26 09:11:00","projectName":"datasketches-java","commitID":"f28e794c6445199824a2ba26e6e17f003cc94d7a"}