{"classFile":"TestQueryResult","className":"TestQueryResult","packages":"org.apache.commons.configuration2.tree","methodInfos":[{"md5":"Q7w0QOF5m9Ujuh5QfNIllw==","methodName":"testIsAttributeResultTrue","parameters":"[]"},{"md5":"mvU4/d58InDlUTP798F6Aw==","methodName":"testIsAttributeResultFalse","parameters":"[]"},{"md5":"LjmRGurwSnsN7WnMbOf35w==","methodName":"testGetAttributeValue","parameters":"[]"},{"md5":"BNK+Jk3Bjfx+opnch9oXnw==","methodName":"testGetAttributeValueNoAttributeResult","parameters":"[]"},{"md5":"pOMPh4Zr1n4bjfJcKs30/w==","methodName":"testEqualsFalse","parameters":"[]"},{"md5":"F2V3VWpoydbAHhvsiygjQQ==","methodName":"testEqualsOtherObjects","parameters":"[]"},{"md5":"GzqUuQj2ptwmVW51mGoZng==","methodName":"testToStringNodeResult","parameters":"[]"},{"md5":"YFjXFgJ4Ta69hBMxBygylw==","methodName":"testToStringAttributeResult","parameters":"[]"}],"addLines":[65,76,87,100,128,130,148,160,172,174],"delLines":[65,76,87,100,128,130,148,160,172,174],"type":"MODIFY","path":"src/test/java/org/apache/commons/configuration2/tree/TestQueryResult.java","pro_Commit":"fa5dbfaf68973a204dc09acb42909ff5bd39ff70","pro_Date":"2018-09-28 06:24:23","sha1":"df3d99be3d8d2c6538adae296620c31bca70aed1","file_Date":"2018-09-28 06:24:23","projectName":"commons-configuration","commitID":"fa5dbfaf68973a204dc09acb42909ff5bd39ff70"}