{"classFile":"TestCombinedConfiguration","className":"TestCombinedConfiguration","packages":"org.apache.commons.configuration","methodInfos":[{"md5":"qtgcZRUL2yygrwrbcan24Q==","methodName":"testGetSourcesMultiSources","parameters":"[]"},{"md5":"iLqb779xBXpBh+gQAWOTeA==","methodName":"testGetSourcesUnknownKey","parameters":"[]"}],"addLines":[554,555,556,557,558,559,560,561,562,563,564,565,566,567,568,569,570,571,572,573,574,575,576,577,578,579,580,581,582],"delLines":[],"type":"MODIFY","path":"src/test/java/org/apache/commons/configuration/TestCombinedConfiguration.java","pro_Commit":"ba18fc0c5c0bd18ea0641a206eab1b9e6e692347","pro_Date":"2014-04-14 00:03:37","sha1":"3d97eb66d1da01dc150398decb766023a700b68d","file_Date":"2014-04-14 00:03:37","projectName":"commons-configuration","commitID":"ba18fc0c5c0bd18ea0641a206eab1b9e6e692347"}