{"repository":"zeppelin","prod_path":"zeppelin-zengine/src/main/java/org/apache/zeppelin/plugin/PluginManager.java","test_path":"zeppelin-zengine/src/test/java/org/apache/zeppelin/plugin/PluginManagerTest.java","prod_time":"2020-01-19 15:44:36","test_time":"2020-02-13 17:33:25","add_annotation_line":0,"add_call_line":0,"add_classname_line":0,"add_condition_line":0,"add_field_line":0,"add_import_line":0,"add_packageid_line":0,"add_parameter_line":0,"add_return_line":0,"del_annotation_line":0,"del_call_line":2,"del_classname_line":0,"del_condition_line":1,"del_field_line":0,"del_import_line":0,"del_packageid_line":0,"del_parameter_line":0,"del_return_line":0,"label":"NEGATIVE","pro_Commit":"52d2b4b0b2430573e4d088ea4099c2b4b9bc8a5c","test_Commit":"7bea72d71a062afd4aab48e6bc1669bfbb9de04b","true_label":"NEGATIVE"}