{"classFile":"CloseShieldInputTest","className":"CloseShieldInputTest","packages":"org.cactoos.io","methodInfos":[{"md5":"lZunrMLozei1p2Vd00frpg==","methodName":"preventsOriginalStreamToBeClosed","parameters":"[]"},{"md5":"J4PWafkanywYL6uQJ9bD2Q==","methodName":"readsContent","parameters":"[]"}],"addLines":[34,38,47,66],"delLines":[34,38,47,66],"type":"RENAME","path":"src/test/java/org/cactoos/io/CloseShieldInputTest.java","pro_Commit":"457e647e0c6a63047dc7ee76b0620ea2e7d7a72f","label":null,"predict":null,"commitID":"457e647e0c6a63047dc7ee76b0620ea2e7d7a72f","pro_Date":"2021-03-15 01:48:02","file_Date":"2021-03-15 01:48:02","projectName":"cactoos","sha1":"058eb747df97f047aed9e111c38c87b6e92ba124","pro_Path":null}