{"classFile":"IterableOfTest","className":"IterableOfTest","packages":"org.cactoos.iterable","methodInfos":[{"md5":"VS86K+F+kdqzHE8u/cMhhg==","methodName":"convertsScalarsToIterable","parameters":"[]"},{"md5":"DvhvClSvKrTzrOihgAxDMQ==","methodName":"convertsObjectsToIterable","parameters":"[]"}],"addLines":[33,40,47,61],"delLines":[33,40,47,61,70,71,72,73,74,75,76,77,78,79,80,81,82,83,84,85,86,87,88,89],"type":"RENAME","path":"src/test/java/org/cactoos/iterable/IterableOfTest.java","pro_Commit":"31a1ca6d046941c882021c71c6a1b3b082851bf2","label":null,"predict":null,"commitID":"31a1ca6d046941c882021c71c6a1b3b082851bf2","pro_Date":"2017-08-03 12:33:04","file_Date":"2017-08-03 12:33:04","projectName":"cactoos","sha1":"f5258f34a8c2b99fcd38499c37eec70ba8ab3c03","pro_Path":null}