{"classFile":"SelectTest","className":"SelectTest","packages":"net.sf.jsqlparser.statement.select","methodInfos":[{"md5":"slTdIyWYSdqxy2UJDqK2zA==","methodName":"testKeywordSkipIssue1136","parameters":"[]"}],"addLines":[4483,4484,4485,4486,4487],"delLines":[],"type":"MODIFY","path":"src/test/java/net/sf/jsqlparser/statement/select/SelectTest.java","pro_Commit":"6cff161dacc1e6feeccce709ca08220e576836be","pro_Date":"2020-08-24 04:07:53","sha1":"4fe1c4418b4415a71f4a4ec9a77b48edb49ce768","file_Date":"2021-04-11 05:09:19","projectName":"JSqlParser","commitID":"ba9b8d7a6f24274fe1d06009fc6d639be85afef4"}