{"classFile":"ArcsSetTest","className":"ArcsSetTest","packages":"org.apache.commons.geometry.spherical.oned","methodInfos":[{"md5":"nuTBcPhm4oA7rN//EuX4kA==","methodName":"testArc","parameters":"[]"},{"md5":"1SZuklg7ok8AvjXWLug3XQ==","methodName":"testWrapAround2PiArc","parameters":"[]"},{"md5":"cojmmfoAF6IchlWXcBGzjA==","methodName":"testSplitOver2Pi","parameters":"[]"},{"md5":"MCd6D8p43R/tNrFGyVDAWQ==","methodName":"testSplitAtEnd","parameters":"[]"},{"md5":"YaPw2nVzXXrpnl1VrwZSDw==","methodName":"testWrongInterval","parameters":"[]"},{"md5":"0b81rlQ5/+dElSDENgSdyg==","methodName":"testFullEqualEndPoints","parameters":"[]"},{"md5":"VzIByRN4W+H3u1XMs/QMNA==","methodName":"testFullCircle","parameters":"[]"},{"md5":"rg2qIE6lrZnKj6mPv6W9ug==","methodName":"testEmpty","parameters":"[]"},{"md5":"1tk831SCr+UKPXbN+uQSrQ==","methodName":"testTiny","parameters":"[]"},{"md5":"Oxf4+MUa21QnCQb3wyIrkQ==","methodName":"testSpecialConstruction","parameters":"[]"},{"md5":"Zvd20UNe8akk2xlEOCzOig==","methodName":"testDifference","parameters":"[]"},{"md5":"MOI8Rc/S4yKK6bHjjROJIA==","methodName":"testIntersection","parameters":"[]"},{"md5":"h8YNA9luWcGT59GNm5y02Q==","methodName":"testMultiple","parameters":"[]"},{"md5":"565ochr6qZUOY+0teUaf2w==","methodName":"testSinglePoint","parameters":"[]"},{"md5":"OyOnSLQnHAmAHNiRHJ0GYg==","methodName":"testIteration","parameters":"[]"},{"md5":"+DhubxZUcb49ijCA7YCpPg==","methodName":"testEmptyTree","parameters":"[]"},{"md5":"Pd5EsMbsUehFsxXzO2/Yfw==","methodName":"testShiftedAngles","parameters":"[]"},{"md5":"hJL6y1x9QOFGy5Jw3O/7tg==","methodName":"testInconsistentState","parameters":"[]"},{"md5":"3H3RvlaLLaAMnIHBoEdlIQ==","methodName":"testSide","parameters":"[]"},{"md5":"jTgPey0dDJOVfqtIJAPxMA==","methodName":"testSideEmbedded","parameters":"[]"},{"md5":"XgqhkcUJRuGdIFQvxzL9RA==","methodName":"testSideOverlapping","parameters":"[]"},{"md5":"WQ4UPDtDpLU4emqtu2gsFw==","methodName":"testSideHyper","parameters":"[]"},{"md5":"hhkyI5perZKoTnRfNYZohA==","methodName":"testSplitEmbedded","parameters":"[]"},{"md5":"liFnmWQHVF5bRHbX/Rq4UQ==","methodName":"testSplitOverlapping","parameters":"[]"},{"md5":"28lg0uujH+OaNfjh+/QSeg==","methodName":"testFarSplit","parameters":"[]"},{"md5":"B4By+nweQIbxPDX3wJkedA==","methodName":"testSplitWithinEpsilon","parameters":"[]"},{"md5":"3LmziWdLaVyLBKDXIyoxeg==","methodName":"testSideSplitConsistency","parameters":"[]"}],"addLines":[31,32,39,40,41,42,43,46,47,48,56,57,62,63,64,72,73,78,79,95,96,121,126,127,133,134,135,140,141,147,148,149,154,155,156,162,163,164,166,167,173,174,175,176,177,179,180,186,189,190,192,195,196,218,219,220,221,229,230,233,234,235,236,238,241,242,263,264,265,266,275,276,277,278,279,292,293,294,295,301,307,308,320,321,326,327,341,347,348,356,370,371,372,383,388,389,393,396,399,402,405,408,411,418,419,421,422,423,424,430,431,433,434,435,436,441,443,449,450,452,455,457,458,459,460,461,463,464,466,469,471,472,473,475,476,477,478,480,484,486,487,489,492,494,495,503,504,506,509,511,512,513,515,516,518,521,523,524,525,527,528,530,533,535,536,537,539,540,542,545,547,548,549,551,552,558,559,563,564,565,567,568,569,575,576,579,580,589,591,592],"delLines":[39,40,41,49,50,55,56,57,65,66,71,72,88,89,114,119,120,126,127,128,133,134,140,141,142,147,148,149,155,156,157,159,160,166,167,168,169,170,172,173,179,182,183,185,188,189,211,212,213,214,222,223,226,227,228,229,231,234,235,256,257,258,259,268,269,270,271,272,285,286,287,288,294,300,301,313,314,319,320,334,340,341,349,363,364,365,376,381,382,386,389,392,395,398,401,404,411,412,414,415,416,417,423,424,426,427,428,429,434,436,442,443,445,448,450,451,452,453,454,456,457,459,462,464,465,466,468,469,470,471,473,477,479,480,482,485,487,488,496,497,499,502,504,505,506,508,509,511,514,516,517,518,520,521,523,526,528,529,530,532,533,535,538,540,541,542,544,545,551,552,556,557,558,560,561,562,568,571,572,582,583],"type":"MODIFY","path":"commons-geometry-spherical/src/test/java/org/apache/commons/geometry/spherical/oned/ArcsSetTest.java","pro_Commit":"6e83c6a08a36a644a978d1448bf0d1265e4a5984","pro_Date":"2019-02-02 08:06:46","sha1":"1171665aa6a1afd325a828f83f6e71a4952fc3e0","file_Date":"2019-02-02 08:06:46","projectName":"commons-geometry","commitID":"6e83c6a08a36a644a978d1448bf0d1265e4a5984"}