{"classFile":"LineConvexSubsetTest","className":"LineConvexSubsetTest","packages":"org.apache.commons.geometry.euclidean.twod","methodInfos":[{"md5":"PkEuD9/l8IAWlyZGtm2ajQ==","methodName":"testFromInterval_intervalArg_finite","parameters":"[]"},{"md5":"JVlXfBUzLRUN3bPEes9OpA==","methodName":"testFromInterval_intervalArg_full","parameters":"[]"},{"md5":"hVKHiPWPE2JFMpOo63k2CQ==","methodName":"testFromInterval_intervalArg_positiveHalfSpace","parameters":"[]"},{"md5":"SQWqjjKhxsne+C7BmNilkA==","methodName":"testFromInterval_intervalArg_negativeHalfSpace","parameters":"[]"},{"md5":"uRGpE+n4T2gz3SsyOAdRKw==","methodName":"testFromInterval_doubleArgs_finite","parameters":"[]"},{"md5":"6vdEim++xVgeg7Wn3KnS+w==","methodName":"testFromInterval_doubleArgs_full","parameters":"[]"},{"md5":"75gnyEgOwRRqpvra9G26HQ==","methodName":"testFromInterval_doubleArgs_positiveHalfSpace","parameters":"[]"},{"md5":"7UWaJngXZE6DTUTcfhcBXg==","methodName":"testFromInterval_doubleArgs_negativeHalfSpace","parameters":"[]"},{"md5":"erbAwW7n7ZEuN6z3g2bVRA==","methodName":"testFromInterval_doubleArgs_invalid","parameters":"[]"},{"md5":"K9J7RWcgn3x5D3DgUYWLdw==","methodName":"testToConvex","parameters":"[]"},{"md5":"USapcIzi6JVuKv66liUpOg==","methodName":"testIntersection_line","parameters":"[]"},{"md5":"PwOot92IG3cSquv3Bd2iKQ==","methodName":"testIntersection_lineSegment","parameters":"[]"},{"md5":"qzNCfWrtexRSluOpWDpczg==","methodName":"testSplit_finite","parameters":"[]"},{"md5":"xhdOGeN6tUwlm1QdWCuIbA==","methodName":"testSplit_full","parameters":"[]"},{"md5":"Vub+pYdgfu3jpgumzJcDhA==","methodName":"testSplit_positiveHalfSpace","parameters":"[]"},{"md5":"hhkY1idvLb7ROfonumNrtw==","methodName":"testSplit_negativeHalfSpace","parameters":"[]"},{"md5":"6P40H66HxAjmt6Xg8w3A9g==","methodName":"checkInterval","parameters":"[final Interval expected, final Interval actual]"},{"md5":"6rBRy/bvPeuaXpR/LuAvaw==","methodName":"checkFinite","parameters":"[final LineConvexSubset segment, final Vector2D start, final Vector2D end]"},{"md5":"qpM8G8j4j3+F7e0897ER8w==","methodName":"checkFinite","parameters":"[final LineConvexSubset segment, final Vector2D start, final Vector2D end, final DoublePrecisionContext precision]"},{"md5":"eyA9DCVuyJjTNO5Olv9u6A==","methodName":"checkInfinite","parameters":"[final LineConvexSubset segment, final Line line, final Vector2D start, final Vector2D end]"},{"md5":"u19n5spQWsjjAUvrToK7+w==","methodName":"checkInfinite","parameters":"[final LineConvexSubset segment, final Line line, final Vector2D start, final Vector2D end, final DoublePrecisionContext precision]"}],"addLines":[42,43,45,48,51,60,63,79,80,82,85,91,103,104,106,109,115,127,130,133,142,145,160,163,169,180,183,189,200,231,232,235,245,246,248,249,250,265,266,267,268,284,285,286,288,291,295,299,303,307,311,315,323,324,325,327,329,332,336,340,344,348,356,357,358,360,362,365,369,373,377,381,385,393,394,395,397,399,402,406,410,414,418,422,427,432,436,442,453,457,458],"delLines":[42,43,45,48,51,60,63,79,80,82,85,91,103,104,106,109,115,127,130,133,142,145,160,163,169,180,183,189,200,231,232,235,245,246,248,249,250,265,266,267,268,284,285,286,288,291,295,299,303,307,311,315,323,324,325,327,329,332,336,340,344,348,356,357,358,360,362,365,369,373,377,381,385,393,394,395,397,399,402,406,410,414,418,422,427,432,436,442,453,457,458],"type":"MODIFY","path":"commons-geometry-euclidean/src/test/java/org/apache/commons/geometry/euclidean/twod/LineConvexSubsetTest.java","pro_Commit":"eee258978cae8fe4987c2155ddfbd08c73d3c9db","pro_Date":"2020-05-06 09:50:34","sha1":"b675d2cb833a2d59d6fffbdcfda4893a7f761975","file_Date":"2020-07-02 21:04:43","projectName":"commons-geometry","commitID":"b80eca8bf22be86a46b0d8ea3f3a34c045d60710"}