{"classFile":"BackpressureTest","className":"BackpressureTest","packages":"com.github.davidmoten.rtree","methodInfos":[{"md5":"UTk3ie55yis5EIUe+HMEFg==","methodName":"testBackpressureIterateWhenNodeHasMaxChildrenAndIsRoot","parameters":"[]"},{"md5":"yA1DC/aQKjq9+STojh7nPw==","methodName":"testBackpressureRequestZero","parameters":"[]"},{"md5":"nz0gZY6rdYsIBix0MyFnIQ==","methodName":"testBackpressureIterateWhenNodeHasMaxChildrenAndIsNotRoot","parameters":"[]"},{"md5":"0ocCYjbD6jlBrodOc5PYaQ==","methodName":"testBackpressureIterateWhenConditionFailsAgainstNonLeafNode","parameters":"[]"},{"md5":"HkMZo5MixHuHnG2ZTNzl7w==","methodName":"testBackpressureIterateWhenConditionFailsAgainstLeafNode","parameters":"[]"},{"md5":"fXxfmTRQNfMg7OBhC1R5Mg==","methodName":"backpressureSubscriber","parameters":"[final Set<Entry<Object,Rectangle>> found]"}],"addLines":[21,128,130,131,132,133,134,141,143,144,145,146,147,148,166,176,177,180,181,182,183,190,191,195,196,197,198,203,204,205,206,207,208,209,210,211,212,213,214,215,216,217,218,219,220,238],"delLines":[127,129,130,131,132,137,140,142,143,144,145,146,164,174,175,178,179,180,187,188,192,193,194,199,200,201,219],"type":"MODIFY","path":"src/test/java/com/github/davidmoten/rtree/BackpressureTest.java","pro_Commit":"b47c0f615cabeda00ce2e3ebf4f5d9f2e35fbbfd","pro_Date":"2014-11-02 08:10:59","sha1":"f923f4d7e95809ae86eee8103fce794433c5d380","file_Date":"2014-11-11 09:29:20","projectName":"rtree","commitID":"2926926b6b0a224ff7ddc557db9ab70510e26160"}