{"classFile":"LocaleUtilsTest","className":"LocaleUtilsTest","packages":"org.apache.commons.lang3","methodInfos":[{"md5":"wmPVDL2TVNCjj47HBjRMOg==","methodName":"assertValidToLocale","parameters":"[final String language]"},{"md5":"Tn15KonL/QxjGB1T/tGa8Q==","methodName":"assertValidToLocale","parameters":"[final String localeString, final String language, final String country]"},{"md5":"pMgx2XCdNK2v6Q7mWE+gCA==","methodName":"assertValidToLocale","parameters":"[final String localeString, final String language, final String country, final String variant]"},{"md5":"x9l/ISln30KsJkOEQMpU9Q==","methodName":"assertLocaleLookupList","parameters":"[final Locale locale, final Locale defaultLocale, final Locale[] expected]"},{"md5":"sVHZ3XSTj+nsvc8OR9rMTg==","methodName":"assertLanguageByCountry","parameters":"[final String country, final String[] languages]"},{"md5":"Ir6I//zbzPhTFPQ20X+zSA==","methodName":"assertCountriesByLanguage","parameters":"[final String language, final String[] countries]"},{"md5":"aGe224rB/zDnByEepBuecg==","methodName":"assertUnmodifiableCollection","parameters":"[final Collection<?> coll]"}],"addLines":[83,99,117,118,243,390,441,484],"delLines":[83,99,117,118,243,390,441,484],"type":"MODIFY","path":"src/test/java/org/apache/commons/lang3/LocaleUtilsTest.java","pro_Commit":"5bd622dab027ef37001a630a7c825c5b8c19d1db","pro_Date":"2013-01-22 15:07:42","sha1":"64dd3ead06394a8d5c9122cfb899043439d5b02b","file_Date":"2013-01-22 15:07:42","projectName":"commons-lang","commitID":"5bd622dab027ef37001a630a7c825c5b8c19d1db"}