{"classFile":"CompareToBuilderTest","className":"CompareToBuilderTest","packages":"org.apache.commons.lang3.builder","methodInfos":[{"md5":"rbOtSF45kEhyDyRKxIWg6g==","methodName":"testReflectionCompareEx1","parameters":"[]"},{"md5":"o9n58SQwDv8PWleIKVEyLQ==","methodName":"testReflectionCompareEx2","parameters":"[]"},{"md5":"BOvYvTIYKli9v64fWI9LJw==","methodName":"testObjectEx2","parameters":"[]"}],"addLines":[107,113,289],"delLines":[21,108,111,113,114,115,116,119,123,125,126,298,302,304,305],"type":"MODIFY","path":"src/test/java/org/apache/commons/lang3/builder/CompareToBuilderTest.java","pro_Commit":"b819343483d33cc529b785935cea9bfc2fc080e5","pro_Date":"2012-04-06 01:53:39","sha1":"77d7edba42567efb6bdcb06807903852a3e922cf","file_Date":"2012-09-19 08:31:53","projectName":"commons-lang","commitID":"8cb5f67c584cbcadd50fb4eead2f6b8983f19951"}