{"classFile":"ObjectUtilsTest","className":"ObjectUtilsTest","packages":"org.apache.commons.lang3","methodInfos":[{"md5":"LVLC4D5VWcAUoLFCd/pS1A==","methodName":"testFirstNonNull","parameters":"[]"},{"md5":"+PWGMzopiQG0eEX4e8UVQQ==","methodName":"testToString_Object","parameters":"[]"},{"md5":"Q0JjVwc7L1RQhj55YoiBQg==","methodName":"testToString_ObjectString","parameters":"[]"},{"md5":"3JTysy99CPwgdnZjo+SoQw==","methodName":"testMax","parameters":"[]"},{"md5":"dlR7iIXfUNN6FSdnzfKICg==","methodName":"testMin","parameters":"[]"}],"addLines":[83,276,282,318,344],"delLines":[83,276,282,318,344],"type":"MODIFY","path":"src/test/java/org/apache/commons/lang3/ObjectUtilsTest.java","pro_Commit":"96c8ea2fb3719e2f6e3d7a4d7b46718f26515a86","pro_Date":"2016-10-24 04:09:43","sha1":"b57ae2d45a4d524a9d5092c5d68f503247f02e65","file_Date":"2017-02-15 06:10:56","projectName":"commons-lang","commitID":"ce1bd5785d05d3df324e1169aab4abd45f4281f7"}