{"classFile":"ComparableTextTest","className":"ComparableTextTest","packages":"org.cactoos.text","methodInfos":[{"md5":"2Win9k9hCO5qU6ZeZ6KZvw==","methodName":"equalsToItself","parameters":"[]"}],"addLines":[76,77,78,79,80,81,82,83,84,85,86,87],"delLines":[],"type":"MODIFY","path":"src/test/java/org/cactoos/text/ComparableTextTest.java","pro_Commit":"cb7299fbcc6c2afb31bf47dd5783dd12e8e4b2f5","pro_Date":"2019-01-21 02:11:04","sha1":"ae2b0811aa70508703c6a28b345a4012b2676a22","file_Date":"2019-01-21 02:37:02","projectName":"cactoos","commitID":"4391921e974512223908ad5bc0e92d7937d491b0"}