{"classFile":"TailInputTest","className":"TailInputTest","packages":"org.cactoos.io","methodInfos":[{"md5":"KAqegPKbp6yw5uYN3KNSzw==","methodName":"tailsOnLongStream","parameters":"[]"},{"md5":"PriKP8QKudsLbJdXo+xSMg==","methodName":"tailsOnExactStream","parameters":"[]"},{"md5":"Ki79opNvhhCBhkUMO8hoEQ==","methodName":"tailsOnExactStreamAndBuffer","parameters":"[]"},{"md5":"9jhoIhVizu89vdQKyNjWSw==","methodName":"tailsOnShorterStream","parameters":"[]"},{"md5":"2sVjEQgsI0w668rukJYzaA==","methodName":"failsIfBufferSizeSmallerThanTailSize","parameters":"[]"},{"md5":"y8PWgYPqWzrbhBTDUGysbQ==","methodName":"generate","parameters":"[final int size]"}],"addLines":[1,2,3,4,5,6,7,8,9,10,11,12,13,14,15,16,17,18,19,20,21,22,23,24,25,26,27,28,29,30,31,32,33,34,35,36,37,38,39,40,41,42,43,44,45,46,47,48,49,50,51,52,53,54,55,56,57,58,59,60,61,62,63,64,65,66,67,68,69,70,71,72,73,74,75,76,77,78,79,80,81,82,83,84,85,86,87,88,89,90,91,92,93,94,95,96,97,98,99,100,101,102,103,104,105,106,107,108,109,110],"delLines":[],"type":"ADD","path":"src/test/java/org/cactoos/io/TailInputTest.java","pro_Commit":"31751c99fff22e71af664540aeff327bb7e1fe1b","pro_Date":"2018-04-24 18:41:36","sha1":"85f64139193d1884528c98f0da072f5fb632f357","file_Date":"2018-04-24 18:41:36","projectName":"cactoos","commitID":"31751c99fff22e71af664540aeff327bb7e1fe1b"}