{"classFile":"PartitionedTest","className":"PartitionedTest","packages":"org.cactoos.iterator","methodInfos":[{"md5":"OkwQUsGZAZ/rhLcQdJsqnw==","methodName":"partitionedOne","parameters":"[]"},{"md5":"wN2wAbvoEIjUQUTOUh/yYQ==","methodName":"partitionedEqualSize","parameters":"[]"}],"addLines":[58,77],"delLines":[],"type":"MODIFY","path":"src/test/java/org/cactoos/iterator/PartitionedTest.java","pro_Commit":"224a684a4d1efee5193572708ce9177858d7a453","pro_Date":"2018-01-16 05:35:44","sha1":"09933a58ea21096fa2f01349c4b123a9e7426442","file_Date":"2018-04-17 03:51:47","projectName":"cactoos","commitID":"63b1e8e59b9a4cc2772c378ac20998b04e90bb21"}