{"classFile":"InputAsBytesTest","className":"InputAsBytesTest","packages":"org.cactoos.io","methodInfos":[{"md5":"5W+Oacz6w5UwT0X1GUHimw==","methodName":"readsInputIntoBytes","parameters":"[]"},{"md5":"k/jDeaqALZ25LlOphvNBKw==","methodName":"readsInputIntoBytesWithSmallBuffer","parameters":"[]"},{"md5":"B0+3WgTOq5s5U/K5l1Xx0w==","methodName":"closesInputStream","parameters":"[]"}],"addLines":[34,94,115,137],"delLines":[34,35,95,116,138],"type":"MODIFY","path":"src/test/java/org/cactoos/io/InputAsBytesTest.java","pro_Commit":"ca05173e764e8316a4a05abd73d620a69e7acee5","pro_Date":"2017-07-17 14:39:46","sha1":"75e158605ead363b59660fd7e94d210c01a5be66","file_Date":"2017-07-25 15:50:04","projectName":"cactoos","commitID":"2337e1458681693eb01ba4a42150ebdacabb89da"}