{"classFile":"CallableOfTest","className":"CallableOfTest","packages":"org.cactoos.scalar","methodInfos":[{"md5":"SzKelMdsBIjRAHAZ8NKGUQ==","methodName":"convertsRunnableIntoCallable","parameters":"[]"},{"md5":"8MrZ648EQGrsTxp3UD84KQ==","methodName":"convertsProcIntoCallable","parameters":"[]"},{"md5":"caJE9T7DJIRDqk84gkfDmA==","methodName":"convertsFuncIntoCallable","parameters":"[]"}],"addLines":[28,38,41,55,76],"delLines":[28,38,41,55,76],"type":"MODIFY","path":"src/test/java/org/cactoos/scalar/CallableOfTest.java","pro_Commit":"0eaa80f21b5f81285dbed5b405771bf4756931da","pro_Date":"2020-09-06 01:08:06","sha1":"99e5d98a161e271259f397784e3ff98933d27f30","file_Date":"2020-09-12 19:29:40","projectName":"cactoos","commitID":"97454478d07f360b68ff98504e803f26d6777ae9"}