{"classFile":"HashCodeTest","className":"HashCodeTest","packages":"org.cactoos.scalar","methodInfos":[{"md5":"LNx8akN/e7OIO+sKT9he1Q==","methodName":"computeHashCode","parameters":"[]"},{"md5":"ElYbDlHErbG5G73IvjB7CA==","methodName":"computeHashCodeWithDefaultValues","parameters":"[]"}],"addLines":[30,49,50,68,69],"delLines":[28,49,50,68,69],"type":"MODIFY","path":"src/test/java/org/cactoos/scalar/HashCodeTest.java","pro_Commit":"95f5a04afd70eb6cd0383c910ee9198b9ffd3119","pro_Date":"2019-11-19 02:53:52","sha1":"c52b95b8b122432a423ca351e3a8f623f917a518","file_Date":"2020-05-09 11:43:26","projectName":"cactoos","commitID":"aa3d431cc8aacdeb447e44b901f6509bc5c9ba8c"}