{"classFile":"SortedTest","className":"SortedTest","packages":"org.cactoos.set","methodInfos":[{"md5":"PgW7WjjJIt7c70K2ZIm5wA==","methodName":"returnsCorrectComparator","parameters":"[]"},{"md5":"4LDH9MayMbJxc3XBwtC3XA==","methodName":"returnsSubset","parameters":"[]"},{"md5":"js6SxYGTgGMFYPYlQyf6gw==","methodName":"returnsHeadset","parameters":"[]"},{"md5":"ImyyBX2gkK5k75EDTRNuzw==","methodName":"returnsTailset","parameters":"[]"},{"md5":"xT3rjGaxEAJStuZuFI9QuA==","methodName":"returnsFirst","parameters":"[]"},{"md5":"FCjZZKS5HAlRd2J4dNys6w==","methodName":"returnsLast","parameters":"[]"}],"addLines":[128,129,130,131,132,133,134,135,136,137,138,139,140,141,142,143,144,145,146,147,148,149,150,151,152,153,154,155,156,157,158,159,160,161,162,163,164,165,166,167,168,169,170,171,172,173,174,175,176,177,178,179,180,181,182,183,184,185,186,187,188,189,190,191,192,193,194,195,196,197,198],"delLines":[],"type":"MODIFY","path":"src/test/java/org/cactoos/set/SortedTest.java","pro_Commit":"37f2408ea3d399879278db9264b8f4f4ed2bdc39","pro_Date":"2020-03-20 18:13:59","sha1":"bc8c9c422a36cb89165391c1360fd92f3ec4909c","file_Date":"2020-03-20 18:13:59","projectName":"cactoos","commitID":"37f2408ea3d399879278db9264b8f4f4ed2bdc39"}