{"repository":"geode","prod_path":"geode-core/src/main/java/org/apache/geode/internal/util/ArgumentRedactor.java","test_path":"geode-core/src/test/java/org/apache/geode/internal/util/ArgumentRedactorTest.java","prod_time":"2017-09-12 03:54:06","test_time":"2021-07-27 00:53:40","add_annotation_line":0,"add_call_line":1,"add_classname_line":0,"add_condition_line":0,"add_field_line":0,"add_import_line":0,"add_packageid_line":0,"add_parameter_line":1,"add_return_line":1,"del_annotation_line":0,"del_call_line":0,"del_classname_line":0,"del_condition_line":0,"del_field_line":0,"del_import_line":0,"del_packageid_line":0,"del_parameter_line":0,"del_return_line":0,"label":"NEGATIVE","pro_Commit":"9b308b6cc2fa9b7324ea62622906bdf0913db768","test_Commit":"693e18c48d1c0e3601c517cb7c5493b54649dc10","true_label":null}