{"classFile":"TestPersistentInstant","className":"TestPersistentInstant","packages":"org.joda.time.contrib.hibernate","methodInfos":[{"md5":"T/oIfcjHv8Fsx6JOfGuGSA==","methodName":"testSimpleStore","parameters":"[]"},{"md5":"o8IJvJGUEEPLD4Jiw6eRfg==","methodName":"setupConfiguration","parameters":"[Configuration cfg]"}],"addLines":[],"delLines":[1,2,3,4,5,6,7,8,9,10,11,12,13,14,15,16,17,18,19,20,21,22,23,24,25,26,27,28,29,30,31,32,33,34,35,36,37,38,39,40,41,42,43,44,45,46,47,48,49,50,51,52,53,54,55,56,57,58,59,60,61,62,63,64,65,66,67,68,69,70,71,72,73,74,75,76,77,78,79,80],"type":"DELETE","path":"JodaTimeContrib/hibernate/src/test/java/org/joda/time/contrib/hibernate/TestPersistentInstant.java","pro_Commit":"72b22654962284bac59c2777131b42a2d1f53228","pro_Date":"2011-05-17 00:58:24","sha1":"1a724dfb1e8f4132df94d4ee595d2cbf9e661cb2","file_Date":"2011-05-17 00:58:24","projectName":"joda-time","commitID":"72b22654962284bac59c2777131b42a2d1f53228"}