{"classFile":"SphericalPolygonsSetTest","className":"SphericalPolygonsSetTest","packages":"org.apache.commons.math3.geometry.spherical.twod","methodInfos":[{"md5":"cLaKxaMjcpSmxmTcS2jBwQ==","methodName":"testFullSphere","parameters":"[]"},{"md5":"0YNrpRD3PgRZIPM/ZXSD2g==","methodName":"testSouthHemisphere","parameters":"[]"}],"addLines":[1,2,3,4,5,6,7,8,9,10,11,12,13,14,15,16,17,18,19,20,21,22,23,24,25,26,27,28,29,30,31,32,33,34,35,36,37,38,39,40,41,42,43,44,45,46,47,48,49,50,51,52,53,54,55,56,57,58,59,60],"delLines":[],"type":"ADD","path":"src/test/java/org/apache/commons/math3/geometry/spherical/twod/SphericalPolygonsSetTest.java","pro_Commit":"2a671338058e46b26a951ba01246b33a67d0eff4","label":null,"predict":null,"commitID":"2a671338058e46b26a951ba01246b33a67d0eff4","pro_Date":"2014-01-04 02:06:20","file_Date":"2014-01-04 02:06:20","projectName":"commons-math","sha1":"7fd92203938819a4b434805649d7dbc675d617b1","pro_Path":null}