{"classFile":"TypeSpecTest","className":"TypeSpecTest","packages":"com.squareup.javawriter.builders","methodInfos":[{"md5":"S8b8URlpDoVEMChwPiqb5g==","methodName":"test","parameters":"[]"},{"md5":"cMoPWHTWTl88VHpM7+83eQ==","methodName":"toString","parameters":"[TypeSpec typeSpec]"}],"addLines":[1,2,3,4,5,6,7,8,9,10,11,12,13,14,15,16,17,18,19,20,21,22,23,24,25,26,27,28,29,30,31,32,33,34,35,36,37,38,39,40,41,42,43,44,45,46,47,48,49,50,51,52,53,54,55,56,57,58],"delLines":[],"type":"ADD","path":"src/test/java/com/squareup/javawriter/builders/TypeSpecTest.java","pro_Commit":"d7b2189e9e91cad8f2fec9b5d5dd3b85ef6ce6b9","label":null,"predict":null,"commitID":"d7b2189e9e91cad8f2fec9b5d5dd3b85ef6ce6b9","pro_Date":"2015-01-08 02:55:49","file_Date":"2015-01-08 02:55:49","projectName":"javapoet","sha1":"8fd68be7907274de5f433b49fad1340b6763ceb6","pro_Path":null}