{"classFile":"StringUtilsTest","className":"StringUtilsTest","packages":"org.apache.commons.codec.binary","methodInfos":[{"md5":"+zi+LjGOfab/Wl52p8xUXw==","methodName":"testNewStringUtf16Be","parameters":"[]"},{"md5":"moIiaw/qeGy8Ej8tbcqHJQ==","methodName":"testNewStringUtf16Le","parameters":"[]"}],"addLines":[36,37,38,39,40,41,180,181,189,190],"delLines":[174,175,183,184],"type":"MODIFY","path":"src/test/java/org/apache/commons/codec/binary/StringUtilsTest.java","pro_Commit":"453c56cff0dbbc0ecefaa7f20b8df6d11d6d12ec","pro_Date":"2012-03-28 22:22:17","sha1":"3cb095bfefbf52d67c415f6447282f4a5510f6f6","file_Date":"2012-09-11 07:58:29","projectName":"commons-codec","commitID":"04955ba87e328cd639d7248bf8d72b413613679c"}