{"classFile":"FieldTypeTest","className":"FieldTypeTest","packages":"com.j256.ormlite.field","methodInfos":[{"md5":"VlSv7YbcdTKPFbZnOP+CqA==","methodName":"testFieldTypeConverter","parameters":"[]"}],"addLines":[159,181,182,183],"delLines":[159,181],"type":"MODIFY","path":"src/test/java/com/j256/ormlite/field/FieldTypeTest.java","pro_Commit":"76ee1a5cccdf0a83f71e1c5ca94300923da9acb1","pro_Date":"2014-02-02 09:14:23","sha1":"3a5b558419a8e7fc1f71e74eafc895532788ddad","file_Date":"2014-03-06 04:52:18","projectName":"ormlite-core","commitID":"16df8c8e1bd3d4c7346be04f1d1a735160b15428"}